pptu/cli.py
pptu/constants.py
pptu/pptu.py
pptu/uploaders/__init__.py
pptu/uploaders/_avistaznetwork.py
pptu/uploaders/_base.py
pptu/uploaders/avistaz.py
pptu/uploaders/broadcasthenet.py
pptu/uploaders/cinemaz.py
pptu/uploaders/hdbits.py
pptu/uploaders/ncore.py
pptu/uploaders/passthepopcorn.py
pptu/uploaders/privatehd.py
pptu/utils.py
pptu-2023.11.6.dist-info/METADATA
pptu-2023.11.6.dist-info/WHEEL
pptu-2023.11.6.dist-info/entry_points.txt
pptu-2023.11.6.dist-info/RECORD
